certbot_dns_strato/__init__.py
certbot_dns_strato/dns_strato.py
certbot_dns_strato-0.2.3.dist-info/licenses/LICENSE
certbot_dns_strato-0.2.3.dist-info/METADATA
certbot_dns_strato-0.2.3.dist-info/WHEEL
certbot_dns_strato-0.2.3.dist-info/entry_points.txt
certbot_dns_strato-0.2.3.dist-info/top_level.txt
certbot_dns_strato-0.2.3.dist-info/RECORD
